ory/__init__.py
ory/annotations/__init__.py
ory/annotations/singleton.py
ory/asyncio/__init__.py
ory/asyncio/async_pod.py
ory/asyncio/async_pool.py
ory/asyncio/async_registry_handler.py
ory/components/__init__.py
ory/components/pod.py
ory/components/pool.py
ory/components/registry_handler.py
ory/ext/__init__.py
ory/ext/exceptions.py
ory/ext/singleton.py
ory/registry/__init__.py
ory/registry/pool_registry.py
ory/states/__init__.py
ory/states/permission.py
nyria_ory-1.0.1.dist-info/LICENSE
nyria_ory-1.0.1.dist-info/METADATA
nyria_ory-1.0.1.dist-info/WHEEL
nyria_ory-1.0.1.dist-info/top_level.txt
nyria_ory-1.0.1.dist-info/RECORD
