Metadata-Version: 2.1
Name: nyria-ory
Version: 1.0.1
Summary: Service Management System
Home-page: https://gitlab.nyria.net/nyria/libaries/ory
Author: Nyria
License: GPL-3.0
License-File: LICENSE
